{
"type": "FeatureCollection",
"name": "geoms_selected",
"crs": { "type": "name", "properties": { "name": "urn:ogc:def:crs:OGC:1.3:CRS84" } },
"features": [
{ "type": "Feature", "properties": { "name": "from_map_1" }, "geometry": { "type": "Point", "coordinates": [ -65.373805, 46.386446 ] } }
]
}
