{
"type": "FeatureCollection",
"name": "Aquaculture",
"crs": { "type": "name", "properties": { "name": "urn:ogc:def:crs:OGC:1.3:CRS84" } },
"features": [
{ "type": "Feature", "properties": { "X_leaflet_id": 126, "feature_type": "marker" }, "geometry": { "type": "Point", "coordinates": [ -67.763672, 46.822617 ] } },
{ "type": "Feature", "properties": { "X_leaflet_id": 132, "feature_type": "marker" }, "geometry": { "type": "Point", "coordinates": [ -65.072021, 45.220743 ] } },
{ "type": "Feature", "properties": { "X_leaflet_id": 138, "feature_type": "marker" }, "geometry": { "type": "Point", "coordinates": [ -66.665039, 44.127028 ] } },
{ "type": "Feature", "properties": { "X_leaflet_id": 145, "feature_type": "marker" }, "geometry": { "type": "Point", "coordinates": [ -60.556641, 45.336702 ] } },
{ "type": "Feature", "properties": { "X_leaflet_id": 151, "feature_type": "marker" }, "geometry": { "type": "Point", "coordinates": [ -61.721191, 44.00862 ] } },
{ "type": "Feature", "properties": { "X_leaflet_id": 157, "feature_type": "marker" }, "geometry": { "type": "Point", "coordinates": [ -61.237793, 42.803462 ] } },
{ "type": "Feature", "properties": { "X_leaflet_id": 163, "feature_type": "marker" }, "geometry": { "type": "Point", "coordinates": [ -65.621338, 42.972502 ] } }
]
}
